trail_db/__init__.py
trail_db/db_import.py
trail_multiply/__init__.py
trail_multiply/multiplication.py
trail_db-0.0.4.dist-info/METADATA
trail_db-0.0.4.dist-info/WHEEL
trail_db-0.0.4.dist-info/top_level.txt
trail_db-0.0.4.dist-info/RECORD
