Metadata-Version: 2.1
Name: trail-db
Version: 0.0.4
Summary: Demo library
Home-page: https://medium-multiply.readthedocs.io/
Author: NP
Author-email: nikolaus@trail-ml.com
License: MIT
Platform: UNKNOWN
Classifier: Intended Audience :: Developers
Classifier: License :: OSI Approved :: MIT License
Classifier: Programming Language :: Python
Classifier: Programming Language :: Python :: 3
Classifier: Programming Language :: Python :: 3.6
Classifier: Programming Language :: Python :: 3.7
Classifier: Programming Language :: Python :: 3.8
Classifier: Programming Language :: Python :: 3.9
Classifier: Operating System :: OS Independent
Requires-Dist: pymongo
Requires-Dist: mlflow
